InterPenet/InterPenet.py
InterPenet/Penetration.py
InterPenet/__init__.py
interpenet-0.0.5.dist-info/licenses/LICENSE
interpenet-0.0.5.dist-info/METADATA
interpenet-0.0.5.dist-info/WHEEL
interpenet-0.0.5.dist-info/top_level.txt
interpenet-0.0.5.dist-info/RECORD
