Metadata-Version: 2.4
Name: InterPenet
Version: 0.0.5
Summary: Probabilistic evaluation of penetration of plate
Home-page: https://github.com/ShinsukeSakai0321/InterPenet
Author: Shinsuke Sakai
Author-email: sakaishin0321@gmail.com
License: MIT
Classifier: Programming Language :: Python :: 3
Classifier: License :: OSI Approved :: MIT License
Classifier: Operating System :: OS Independent
Requires-Python: >=3.6
License-File: LICENSE
Requires-Dist: LimitState
Requires-Dist: matplotlib>=3.7.0
Dynamic: author
Dynamic: author-email
Dynamic: classifier
Dynamic: description
Dynamic: description-content-type
Dynamic: home-page
Dynamic: license
Dynamic: license-file
Dynamic: requires-dist
Dynamic: requires-python
Dynamic: summary
